{
  "hierarchy": {
    "a": "HTMLAnchorElement",
    "HTMLAnchorElement": "HTMLElement",
    "HTMLElement": "Element",
    "Element": "Node",
    "Node": "EventTarget",
    "EventTarget": "Object",
    "abbr": "HTMLElement",
    "address": "HTMLElement",
    "area": "HTMLAreaElement",
    "HTMLAreaElement": "HTMLElement",
    "article": "HTMLElement",
    "aside": "HTMLElement",
    "audio": "HTMLAudioElement",
    "HTMLAudioElement": "HTMLMediaElement",
    "HTMLMediaElement": "HTMLElement",
    "b": "HTMLElement",
    "base": "HTMLBaseElement",
    "HTMLBaseElement": "HTMLElement",
    "bdi": "HTMLElement",
    "bdo": "HTMLElement",
    "blockquote": "HTMLQuoteElement",
    "HTMLQuoteElement": "HTMLElement",
    "body": "HTMLBodyElement",
    "HTMLBodyElement": "HTMLElement",
    "br": "HTMLBRElement",
    "HTMLBRElement": "HTMLElement",
    "button": "HTMLButtonElement",
    "HTMLButtonElement": "HTMLElement",
    "canvas": "HTMLCanvasElement",
    "HTMLCanvasElement": "HTMLElement",
    "caption": "HTMLTableCaptionElement",
    "HTMLTableCaptionElement": "HTMLElement",
    "cite": "HTMLElement",
    "code": "HTMLElement",
    "col": "HTMLTableColElement",
    "HTMLTableColElement": "HTMLElement",
    "colgroup": "HTMLTableColElement",
    "data": "HTMLDataElement",
    "HTMLDataElement": "HTMLElement",
    "datalist": "HTMLDataListElement",
    "HTMLDataListElement": "HTMLElement",
    "dd": "HTMLElement",
    "del": "HTMLModElement",
    "HTMLModElement": "HTMLElement",
    "details": "HTMLDetailsElement",
    "HTMLDetailsElement": "HTMLElement",
    "dfn": "HTMLElement",
    "dialog": "HTMLUnknownElement",
    "HTMLUnknownElement": "HTMLElement",
    "div": "HTMLDivElement",
    "HTMLDivElement": "HTMLElement",
    "dl": "HTMLDListElement",
    "HTMLDListElement": "HTMLElement",
    "dt": "HTMLElement",
    "em": "HTMLElement",
    "embed": "HTMLEmbedElement",
    "HTMLEmbedElement": "HTMLElement",
    "fieldset": "HTMLFieldSetElement",
    "HTMLFieldSetElement": "HTMLElement",
    "figcaption": "HTMLElement",
    "figure": "HTMLElement",
    "footer": "HTMLElement",
    "form": "HTMLFormElement",
    "HTMLFormElement": "HTMLElement",
    "h1": "HTMLHeadingElement",
    "HTMLHeadingElement": "HTMLElement",
    "h2": "HTMLHeadingElement",
    "h3": "HTMLHeadingElement",
    "h4": "HTMLHeadingElement",
    "h5": "HTMLHeadingElement",
    "h6": "HTMLHeadingElement",
    "head": "HTMLHeadElement",
    "HTMLHeadElement": "HTMLElement",
    "header": "HTMLElement",
    "hr": "HTMLHRElement",
    "HTMLHRElement": "HTMLElement",
    "html": "HTMLHtmlElement",
    "HTMLHtmlElement": "HTMLElement",
    "i": "HTMLElement",
    "iframe": "HTMLIFrameElement",
    "HTMLIFrameElement": "HTMLElement",
    "img": "HTMLImageElement",
    "HTMLImageElement": "HTMLElement",
    "input": "HTMLInputElement",
    "HTMLInputElement": "HTMLElement",
    "ins": "HTMLModElement",
    "kbd": "HTMLElement",
    "label": "HTMLLabelElement",
    "HTMLLabelElement": "HTMLElement",
    "legend": "HTMLLegendElement",
    "HTMLLegendElement": "HTMLElement",
    "li": "HTMLLIElement",
    "HTMLLIElement": "HTMLElement",
    "link": "HTMLLinkElement",
    "HTMLLinkElement": "HTMLElement",
    "main": "HTMLElement",
    "map": "HTMLMapElement",
    "HTMLMapElement": "HTMLElement",
    "mark": "HTMLElement",
    "math": "HTMLUnknownElement",
    "menu": "HTMLMenuElement",
    "HTMLMenuElement": "HTMLElement",
    "meta": "HTMLMetaElement",
    "HTMLMetaElement": "HTMLElement",
    "meter": "HTMLMeterElement",
    "HTMLMeterElement": "HTMLElement",
    "nav": "HTMLElement",
    "noscript": "HTMLElement",
    "object": "HTMLObjectElement",
    "HTMLObjectElement": "HTMLElement",
    "ol": "HTMLOListElement",
    "HTMLOListElement": "HTMLElement",
    "optgroup": "HTMLOptGroupElement",
    "HTMLOptGroupElement": "HTMLElement",
    "option": "HTMLOptionElement",
    "HTMLOptionElement": "HTMLElement",
    "output": "HTMLOutputElement",
    "HTMLOutputElement": "HTMLElement",
    "p": "HTMLParagraphElement",
    "HTMLParagraphElement": "HTMLElement",
    "param": "HTMLParamElement",
    "HTMLParamElement": "HTMLElement",
    "picture": "HTMLPictureElement",
    "HTMLPictureElement": "HTMLElement",
    "portal": "HTMLUnknownElement",
    "pre": "HTMLPreElement",
    "HTMLPreElement": "HTMLElement",
    "progress": "HTMLProgressElement",
    "HTMLProgressElement": "HTMLElement",
    "q": "HTMLQuoteElement",
    "rp": "HTMLElement",
    "rt": "HTMLElement",
    "ruby": "HTMLElement",
    "s": "HTMLElement",
    "samp": "HTMLElement",
    "script": "HTMLScriptElement",
    "HTMLScriptElement": "HTMLElement",
    "section": "HTMLElement",
    "select": "HTMLSelectElement",
    "HTMLSelectElement": "HTMLElement",
    "slot": "HTMLSlotElement",
    "HTMLSlotElement": "HTMLElement",
    "small": "HTMLElement",
    "source": "HTMLSourceElement",
    "HTMLSourceElement": "HTMLElement",
    "span": "HTMLSpanElement",
    "HTMLSpanElement": "HTMLElement",
    "strong": "HTMLElement",
    "style": "HTMLStyleElement",
    "HTMLStyleElement": "HTMLElement",
    "sub": "HTMLElement",
    "summary": "HTMLElement",
    "sup": "HTMLElement",
    "svg": "HTMLUnknownElement",
    "table": "HTMLTableElement",
    "HTMLTableElement": "HTMLElement",
    "tbody": "HTMLTableSectionElement",
    "HTMLTableSectionElement": "HTMLElement",
    "td": "HTMLTableCellElement",
    "HTMLTableCellElement": "HTMLElement",
    "template": "HTMLTemplateElement",
    "HTMLTemplateElement": "HTMLElement",
    "textarea": "HTMLTextAreaElement",
    "HTMLTextAreaElement": "HTMLElement",
    "tfoot": "HTMLTableSectionElement",
    "th": "HTMLTableCellElement",
    "thead": "HTMLTableSectionElement",
    "time": "HTMLTimeElement",
    "HTMLTimeElement": "HTMLElement",
    "title": "HTMLTitleElement",
    "HTMLTitleElement": "HTMLElement",
    "tr": "HTMLTableRowElement",
    "HTMLTableRowElement": "HTMLElement",
    "track": "HTMLTrackElement",
    "HTMLTrackElement": "HTMLElement",
    "u": "HTMLElement",
    "ul": "HTMLUListElement",
    "HTMLUListElement": "HTMLElement",
    "var": "HTMLElement",
    "video": "HTMLVideoElement",
    "HTMLVideoElement": "HTMLMediaElement",
    "wbr": "HTMLElement",
    "animate": "HTMLUnknownElement",
    "animateMotion": "HTMLUnknownElement",
    "animateTransform": "HTMLUnknownElement",
    "circle": "HTMLUnknownElement",
    "clipPath": "HTMLUnknownElement",
    "defs": "HTMLUnknownElement",
    "desc": "HTMLUnknownElement",
    "discard": "HTMLUnknownElement",
    "ellipse": "HTMLUnknownElement",
    "feBlend": "HTMLUnknownElement",
    "feColorMatrix": "HTMLUnknownElement",
    "feComponentTransfer": "HTMLUnknownElement",
    "feComposite": "HTMLUnknownElement",
    "feConvolveMatrix": "HTMLUnknownElement",
    "feDiffuseLighting": "HTMLUnknownElement",
    "feDisplacementMap": "HTMLUnknownElement",
    "feDistantLight": "HTMLUnknownElement",
    "feDropShadow": "HTMLUnknownElement",
    "feFlood": "HTMLUnknownElement",
    "feFuncA": "HTMLUnknownElement",
    "feFuncB": "HTMLUnknownElement",
    "feFuncG": "HTMLUnknownElement",
    "feFuncR": "HTMLUnknownElement",
    "feGaussianBlur": "HTMLUnknownElement",
    "feImage": "HTMLUnknownElement",
    "feMerge": "HTMLUnknownElement",
    "feMergeNode": "HTMLUnknownElement",
    "feMorphology": "HTMLUnknownElement",
    "feOffset": "HTMLUnknownElement",
    "fePointLight": "HTMLUnknownElement",
    "feSpecularLighting": "HTMLUnknownElement",
    "feSpotLight": "HTMLUnknownElement",
    "feTile": "HTMLUnknownElement",
    "feTurbulence": "HTMLUnknownElement",
    "filter": "HTMLUnknownElement",
    "foreignObject": "HTMLUnknownElement",
    "g": "HTMLUnknownElement",
    "hatch": "HTMLUnknownElement",
    "hatchpath": "HTMLUnknownElement",
    "image": "HTMLElement",
    "line": "HTMLUnknownElement",
    "linearGradient": "HTMLUnknownElement",
    "marker": "HTMLUnknownElement",
    "mask": "HTMLUnknownElement",
    "mesh": "HTMLUnknownElement",
    "meshgradient": "HTMLUnknownElement",
    "meshpatch": "HTMLUnknownElement",
    "meshrow": "HTMLUnknownElement",
    "metadata": "HTMLUnknownElement",
    "mpath": "HTMLUnknownElement",
    "path": "HTMLUnknownElement",
    "pattern": "HTMLUnknownElement",
    "polygon": "HTMLUnknownElement",
    "polyline": "HTMLUnknownElement",
    "radialGradient": "HTMLUnknownElement",
    "rect": "HTMLUnknownElement",
    "set": "HTMLUnknownElement",
    "stop": "HTMLUnknownElement",
    "switch": "HTMLUnknownElement",
    "symbol": "HTMLUnknownElement",
    "text": "HTMLUnknownElement",
    "textPath": "HTMLUnknownElement",
    "tspan": "HTMLUnknownElement",
    "use": "HTMLUnknownElement",
    "view": "HTMLUnknownElement"
  },
  "ownProps": {
    "HTMLAnchorElement": [
      "toString",
      "target",
      "download",
      "ping",
      "rel",
      "referrerPolicy",
      "relList",
      "hreflang",
      "type",
      "text",
      "coords",
      "charset",
      "name",
      "rev",
      "shape",
      "href",
      "origin",
      "protocol",
      "username",
      "password",
      "host",
      "hostname",
      "port",
      "pathname",
      "search",
      "hash",
      "constructor"
    ],
    "HTMLElement": [
      "click",
      "attachInternals",
      "focus",
      "blur",
      "title",
      "lang",
      "dir",
      "innerText",
      "hidden",
      "accessKey",
      "accessKeyLabel",
      "draggable",
      "contentEditable",
      "isContentEditable",
      "spellcheck",
      "inputMode",
      "enterKeyHint",
      "nonce",
      "offsetParent",
      "offsetTop",
      "offsetLeft",
      "offsetWidth",
      "offsetHeight",
      "oncopy",
      "oncut",
      "onpaste",
      "style",
      "onabort",
      "onblur",
      "onfocus",
      "onauxclick",
      "onbeforeinput",
      "oncanplay",
      "oncanplaythrough",
      "onchange",
      "onclick",
      "onclose",
      "oncontextmenu",
      "oncuechange",
      "ondblclick",
      "ondrag",
      "ondragend",
      "ondragenter",
      "ondragexit",
      "ondragleave",
      "ondragover",
      "ondragstart",
      "ondrop",
      "ondurationchange",
      "onemptied",
      "onended",
      "onformdata",
      "oninput",
      "oninvalid",
      "onkeydown",
      "onkeypress",
      "onkeyup",
      "onload",
      "onloadeddata",
      "onloadedmetadata",
      "onloadend",
      "onloadstart",
      "onmousedown",
      "onmouseenter",
      "onmouseleave",
      "onmousemove",
      "onmouseout",
      "onmouseover",
      "onmouseup",
      "onwheel",
      "onpause",
      "onplay",
      "onplaying",
      "onprogress",
      "onratechange",
      "onreset",
      "onresize",
      "onscroll",
      "onsecuritypolicyviolation",
      "onseeked",
      "onseeking",
      "onselect",
      "onslotchange",
      "onstalled",
      "onsubmit",
      "onsuspend",
      "ontimeupdate",
      "onvolumechange",
      "onwaiting",
      "onselectstart",
      "onselectionchange",
      "ontoggle",
      "onpointercancel",
      "onpointerdown",
      "onpointerup",
      "onpointermove",
      "onpointerout",
      "onpointerover",
      "onpointerenter",
      "onpointerleave",
      "ongotpointercapture",
      "onlostpointercapture",
      "onmozfullscreenchange",
      "onmozfullscreenerror",
      "onanimationcancel",
      "onanimationend",
      "onanimationiteration",
      "onanimationstart",
      "ontransitioncancel",
      "ontransitionend",
      "ontransitionrun",
      "ontransitionstart",
      "onwebkitanimationend",
      "onwebkitanimationiteration",
      "onwebkitanimationstart",
      "onwebkittransitionend",
      "dataset",
      "tabIndex",
      "onerror",
      "constructor"
    ],
    "Element": [
      "getAttributeNames",
      "getAttribute",
      "getAttributeNS",
      "toggleAttribute",
      "setAttribute",
      "setAttributeNS",
      "removeAttribute",
      "removeAttributeNS",
      "hasAttribute",
      "hasAttributeNS",
      "hasAttributes",
      "closest",
      "matches",
      "webkitMatchesSelector",
      "getElementsByTagName",
      "getElementsByTagNameNS",
      "getElementsByClassName",
      "insertAdjacentElement",
      "insertAdjacentText",
      "mozMatchesSelector",
      "setPointerCapture",
      "releasePointerCapture",
      "hasPointerCapture",
      "setCapture",
      "releaseCapture",
      "getAttributeNode",
      "setAttributeNode",
      "removeAttributeNode",
      "getAttributeNodeNS",
      "setAttributeNodeNS",
      "getClientRects",
      "getBoundingClientRect",
      "scrollIntoView",
      "scroll",
      "scrollTo",
      "scrollBy",
      "insertAdjacentHTML",
      "querySelector",
      "querySelectorAll",
      "attachShadow",
      "requestFullscreen",
      "mozRequestFullScreen",
      "requestPointerLock",
      "animate",
      "getAnimations",
      "before",
      "after",
      "replaceWith",
      "remove",
      "prepend",
      "append",
      "replaceChildren",
      "namespaceURI",
      "prefix",
      "localName",
      "tagName",
      "id",
      "className",
      "classList",
      "part",
      "attributes",
      "scrollTop",
      "scrollLeft",
      "scrollWidth",
      "scrollHeight",
      "clientTop",
      "clientLeft",
      "clientWidth",
      "clientHeight",
      "scrollTopMax",
      "scrollLeftMax",
      "innerHTML",
      "outerHTML",
      "shadowRoot",
      "assignedSlot",
      "slot",
      "onfullscreenchange",
      "onfullscreenerror",
      "previousElementSibling",
      "nextElementSibling",
      "children",
      "firstElementChild",
      "lastElementChild",
      "childElementCount",
      "constructor"
    ],
    "Node": [
      "getRootNode",
      "hasChildNodes",
      "insertBefore",
      "appendChild",
      "replaceChild",
      "removeChild",
      "normalize",
      "cloneNode",
      "isSameNode",
      "isEqualNode",
      "compareDocumentPosition",
      "contains",
      "lookupPrefix",
      "lookupNamespaceURI",
      "isDefaultNamespace",
      "nodeType",
      "nodeName",
      "baseURI",
      "isConnected",
      "ownerDocument",
      "parentNode",
      "parentElement",
      "childNodes",
      "firstChild",
      "lastChild",
      "previousSibling",
      "nextSibling",
      "nodeValue",
      "textContent",
      "ELEMENT_NODE",
      "ATTRIBUTE_NODE",
      "TEXT_NODE",
      "CDATA_SECTION_NODE",
      "ENTITY_REFERENCE_NODE",
      "ENTITY_NODE",
      "PROCESSING_INSTRUCTION_NODE",
      "COMMENT_NODE",
      "DOCUMENT_NODE",
      "DOCUMENT_TYPE_NODE",
      "DOCUMENT_FRAGMENT_NODE",
      "NOTATION_NODE",
      "DOCUMENT_POSITION_DISCONNECTED",
      "DOCUMENT_POSITION_PRECEDING",
      "DOCUMENT_POSITION_FOLLOWING",
      "DOCUMENT_POSITION_CONTAINS",
      "DOCUMENT_POSITION_CONTAINED_BY",
      "DOCUMENT_POSITION_IMPLEMENTATION_SPECIFIC",
      "constructor"
    ],
    "EventTarget": [
      "addEventListener",
      "removeEventListener",
      "dispatchEvent",
      "constructor"
    ],
    "Object": [
      "toString",
      "toLocaleString",
      "valueOf",
      "hasOwnProperty",
      "isPrototypeOf",
      "propertyIsEnumerable",
      "__defineGetter__",
      "__defineSetter__",
      "__lookupGetter__",
      "__lookupSetter__",
      "__proto__",
      "constructor"
    ],
    "HTMLAreaElement": [
      "toString",
      "alt",
      "coords",
      "shape",
      "target",
      "download",
      "ping",
      "rel",
      "referrerPolicy",
      "relList",
      "noHref",
      "href",
      "origin",
      "protocol",
      "username",
      "password",
      "host",
      "hostname",
      "port",
      "pathname",
      "search",
      "hash",
      "constructor"
    ],
    "HTMLAudioElement": [
      "constructor"
    ],
    "HTMLMediaElement": [
      "load",
      "canPlayType",
      "fastSeek",
      "play",
      "pause",
      "addTextTrack",
      "mozCaptureStream",
      "mozCaptureStreamUntilEnded",
      "mozGetMetadata",
      "setMediaKeys",
      "seekToNextFrame",
      "error",
      "src",
      "currentSrc",
      "crossOrigin",
      "networkState",
      "preload",
      "buffered",
      "readyState",
      "seeking",
      "currentTime",
      "duration",
      "paused",
      "defaultPlaybackRate",
      "playbackRate",
      "played",
      "seekable",
      "ended",
      "autoplay",
      "loop",
      "controls",
      "volume",
      "muted",
      "defaultMuted",
      "textTracks",
      "srcObject",
      "mozPreservesPitch",
      "mozAudioCaptured",
      "mozFragmentEnd",
      "mediaKeys",
      "onencrypted",
      "onwaitingforkey",
      "NETWORK_EMPTY",
      "NETWORK_IDLE",
      "NETWORK_LOADING",
      "NETWORK_NO_SOURCE",
      "HAVE_NOTHING",
      "HAVE_METADATA",
      "HAVE_CURRENT_DATA",
      "HAVE_FUTURE_DATA",
      "HAVE_ENOUGH_DATA",
      "constructor"
    ],
    "HTMLBaseElement": [
      "href",
      "target",
      "constructor"
    ],
    "HTMLQuoteElement": [
      "cite",
      "constructor"
    ],
    "HTMLBodyElement": [
      "text",
      "link",
      "vLink",
      "aLink",
      "bgColor",
      "background",
      "onafterprint",
      "onbeforeprint",
      "onbeforeunload",
      "onhashchange",
      "onlanguagechange",
      "onmessage",
      "onmessageerror",
      "onoffline",
      "ononline",
      "onpagehide",
      "onpageshow",
      "onpopstate",
      "onrejectionhandled",
      "onstorage",
      "onunhandledrejection",
      "onunload",
      "ongamepadconnected",
      "ongamepaddisconnected",
      "constructor"
    ],
    "HTMLBRElement": [
      "clear",
      "constructor"
    ],
    "HTMLButtonElement": [
      "checkValidity",
      "reportValidity",
      "setCustomValidity",
      "autofocus",
      "disabled",
      "form",
      "formAction",
      "formEnctype",
      "formMethod",
      "formNoValidate",
      "formTarget",
      "name",
      "type",
      "value",
      "willValidate",
      "validity",
      "validationMessage",
      "labels",
      "constructor"
    ],
    "HTMLCanvasElement": [
      "getContext",
      "toDataURL",
      "toBlob",
      "captureStream",
      "width",
      "height",
      "mozOpaque",
      "mozPrintCallback",
      "constructor"
    ],
    "HTMLTableCaptionElement": [
      "align",
      "constructor"
    ],
    "HTMLTableColElement": [
      "span",
      "align",
      "ch",
      "chOff",
      "vAlign",
      "width",
      "constructor"
    ],
    "HTMLDataElement": [
      "value",
      "constructor"
    ],
    "HTMLDataListElement": [
      "options",
      "constructor"
    ],
    "HTMLModElement": [
      "cite",
      "dateTime",
      "constructor"
    ],
    "HTMLDetailsElement": [
      "open",
      "constructor"
    ],
    "HTMLUnknownElement": [
      "constructor"
    ],
    "HTMLDivElement": [
      "align",
      "constructor"
    ],
    "HTMLDListElement": [
      "compact",
      "constructor"
    ],
    "HTMLEmbedElement": [
      "getSVGDocument",
      "src",
      "type",
      "width",
      "height",
      "align",
      "name",
      "constructor"
    ],
    "HTMLFieldSetElement": [
      "checkValidity",
      "reportValidity",
      "setCustomValidity",
      "disabled",
      "form",
      "name",
      "type",
      "elements",
      "willValidate",
      "validity",
      "validationMessage",
      "constructor"
    ],
    "HTMLFormElement": [
      "submit",
      "requestSubmit",
      "reset",
      "checkValidity",
      "reportValidity",
      "acceptCharset",
      "action",
      "autocomplete",
      "enctype",
      "encoding",
      "method",
      "name",
      "noValidate",
      "target",
      "elements",
      "length",
      "constructor"
    ],
    "HTMLHeadingElement": [
      "align",
      "constructor"
    ],
    "HTMLHeadElement": [
      "constructor"
    ],
    "HTMLHRElement": [
      "align",
      "color",
      "noShade",
      "size",
      "width",
      "constructor"
    ],
    "HTMLHtmlElement": [
      "version",
      "constructor"
    ],
    "HTMLIFrameElement": [
      "getSVGDocument",
      "src",
      "srcdoc",
      "name",
      "sandbox",
      "allowFullscreen",
      "width",
      "height",
      "referrerPolicy",
      "contentDocument",
      "contentWindow",
      "align",
      "scrolling",
      "frameBorder",
      "longDesc",
      "marginHeight",
      "marginWidth",
      "allow",
      "constructor"
    ],
    "HTMLImageElement": [
      "decode",
      "alt",
      "src",
      "srcset",
      "crossOrigin",
      "useMap",
      "referrerPolicy",
      "isMap",
      "width",
      "height",
      "decoding",
      "loading",
      "naturalWidth",
      "naturalHeight",
      "complete",
      "name",
      "align",
      "hspace",
      "vspace",
      "longDesc",
      "border",
      "sizes",
      "currentSrc",
      "lowsrc",
      "x",
      "y",
      "constructor"
    ],
    "HTMLInputElement": [
      "stepUp",
      "stepDown",
      "checkValidity",
      "reportValidity",
      "setCustomValidity",
      "select",
      "setRangeText",
      "setSelectionRange",
      "mozIsTextField",
      "accept",
      "alt",
      "autocomplete",
      "autofocus",
      "defaultChecked",
      "checked",
      "disabled",
      "form",
      "files",
      "formAction",
      "formEnctype",
      "formMethod",
      "formNoValidate",
      "formTarget",
      "height",
      "indeterminate",
      "list",
      "max",
      "maxLength",
      "min",
      "minLength",
      "multiple",
      "name",
      "pattern",
      "placeholder",
      "readOnly",
      "required",
      "size",
      "src",
      "step",
      "type",
      "defaultValue",
      "value",
      "valueAsDate",
      "valueAsNumber",
      "width",
      "willValidate",
      "validity",
      "validationMessage",
      "labels",
      "selectionStart",
      "selectionEnd",
      "selectionDirection",
      "align",
      "useMap",
      "textLength",
      "webkitEntries",
      "webkitdirectory",
      "constructor"
    ],
    "HTMLLabelElement": [
      "form",
      "htmlFor",
      "control",
      "constructor"
    ],
    "HTMLLegendElement": [
      "form",
      "align",
      "constructor"
    ],
    "HTMLLIElement": [
      "value",
      "type",
      "constructor"
    ],
    "HTMLLinkElement": [
      "disabled",
      "href",
      "crossOrigin",
      "rel",
      "relList",
      "media",
      "hreflang",
      "type",
      "referrerPolicy",
      "sizes",
      "imageSrcset",
      "imageSizes",
      "charset",
      "rev",
      "target",
      "integrity",
      "as",
      "sheet",
      "constructor"
    ],
    "HTMLMapElement": [
      "name",
      "areas",
      "constructor"
    ],
    "HTMLMenuElement": [
      "compact",
      "constructor"
    ],
    "HTMLMetaElement": [
      "name",
      "httpEquiv",
      "content",
      "scheme",
      "constructor"
    ],
    "HTMLMeterElement": [
      "value",
      "min",
      "max",
      "low",
      "high",
      "optimum",
      "labels",
      "constructor"
    ],
    "HTMLObjectElement": [
      "checkValidity",
      "reportValidity",
      "setCustomValidity",
      "getSVGDocument",
      "data",
      "type",
      "name",
      "useMap",
      "form",
      "width",
      "height",
      "contentDocument",
      "contentWindow",
      "willValidate",
      "validity",
      "validationMessage",
      "align",
      "archive",
      "code",
      "declare",
      "hspace",
      "standby",
      "vspace",
      "codeBase",
      "codeType",
      "border",
      "constructor"
    ],
    "HTMLOListElement": [
      "reversed",
      "start",
      "type",
      "compact",
      "constructor"
    ],
    "HTMLOptGroupElement": [
      "disabled",
      "label",
      "constructor"
    ],
    "HTMLOptionElement": [
      "disabled",
      "form",
      "label",
      "defaultSelected",
      "selected",
      "value",
      "text",
      "index",
      "constructor"
    ],
    "HTMLOutputElement": [
      "checkValidity",
      "reportValidity",
      "setCustomValidity",
      "htmlFor",
      "form",
      "name",
      "type",
      "defaultValue",
      "value",
      "willValidate",
      "validity",
      "validationMessage",
      "labels",
      "constructor"
    ],
    "HTMLParagraphElement": [
      "align",
      "constructor"
    ],
    "HTMLParamElement": [
      "name",
      "value",
      "type",
      "valueType",
      "constructor"
    ],
    "HTMLPictureElement": [
      "constructor"
    ],
    "HTMLPreElement": [
      "width",
      "constructor"
    ],
    "HTMLProgressElement": [
      "value",
      "max",
      "position",
      "labels",
      "constructor"
    ],
    "HTMLScriptElement": [
      "src",
      "type",
      "noModule",
      "charset",
      "async",
      "defer",
      "crossOrigin",
      "referrerPolicy",
      "text",
      "event",
      "htmlFor",
      "integrity",
      "constructor"
    ],
    "HTMLSelectElement": [
      "item",
      "namedItem",
      "add",
      "remove",
      "checkValidity",
      "reportValidity",
      "setCustomValidity",
      "autofocus",
      "autocomplete",
      "disabled",
      "form",
      "multiple",
      "name",
      "required",
      "size",
      "type",
      "options",
      "length",
      "selectedOptions",
      "selectedIndex",
      "value",
      "willValidate",
      "validity",
      "validationMessage",
      "labels",
      "constructor"
    ],
    "HTMLSlotElement": [
      "assignedNodes",
      "assignedElements",
      "assign",
      "name",
      "constructor"
    ],
    "HTMLSourceElement": [
      "src",
      "type",
      "srcset",
      "sizes",
      "media",
      "constructor"
    ],
    "HTMLSpanElement": [
      "constructor"
    ],
    "HTMLStyleElement": [
      "disabled",
      "media",
      "type",
      "sheet",
      "constructor"
    ],
    "HTMLTableElement": [
      "createCaption",
      "deleteCaption",
      "createTHead",
      "deleteTHead",
      "createTFoot",
      "deleteTFoot",
      "createTBody",
      "insertRow",
      "deleteRow",
      "caption",
      "tHead",
      "tFoot",
      "tBodies",
      "rows",
      "align",
      "border",
      "frame",
      "rules",
      "summary",
      "width",
      "bgColor",
      "cellPadding",
      "cellSpacing",
      "constructor"
    ],
    "HTMLTableSectionElement": [
      "insertRow",
      "deleteRow",
      "rows",
      "align",
      "ch",
      "chOff",
      "vAlign",
      "constructor"
    ],
    "HTMLTableCellElement": [
      "colSpan",
      "rowSpan",
      "headers",
      "cellIndex",
      "abbr",
      "scope",
      "align",
      "axis",
      "height",
      "width",
      "ch",
      "chOff",
      "noWrap",
      "vAlign",
      "bgColor",
      "constructor"
    ],
    "HTMLTemplateElement": [
      "content",
      "constructor"
    ],
    "HTMLTextAreaElement": [
      "checkValidity",
      "reportValidity",
      "setCustomValidity",
      "select",
      "setRangeText",
      "setSelectionRange",
      "autocomplete",
      "autofocus",
      "cols",
      "disabled",
      "form",
      "maxLength",
      "minLength",
      "name",
      "placeholder",
      "readOnly",
      "required",
      "rows",
      "wrap",
      "type",
      "defaultValue",
      "value",
      "textLength",
      "willValidate",
      "validity",
      "validationMessage",
      "labels",
      "selectionStart",
      "selectionEnd",
      "selectionDirection",
      "constructor"
    ],
    "HTMLTimeElement": [
      "dateTime",
      "constructor"
    ],
    "HTMLTitleElement": [
      "text",
      "constructor"
    ],
    "HTMLTableRowElement": [
      "insertCell",
      "deleteCell",
      "rowIndex",
      "sectionRowIndex",
      "cells",
      "align",
      "ch",
      "chOff",
      "vAlign",
      "bgColor",
      "constructor"
    ],
    "HTMLTrackElement": [
      "kind",
      "src",
      "srclang",
      "label",
      "default",
      "readyState",
      "track",
      "NONE",
      "LOADING",
      "LOADED",
      "ERROR",
      "constructor"
    ],
    "HTMLUListElement": [
      "compact",
      "type",
      "constructor"
    ],
    "HTMLVideoElement": [
      "getVideoPlaybackQuality",
      "width",
      "height",
      "videoWidth",
      "videoHeight",
      "poster",
      "mozParsedFrames",
      "mozDecodedFrames",
      "mozPresentedFrames",
      "mozPaintedFrames",
      "mozFrameDelay",
      "mozHasAudio",
      "constructor"
    ]
  }
}
